{
  "_doc": "Per element (and per prowess card) a list of ranks. Each rank is a list of {type, cv}. Rank 0 = primary; each additional rank has half the probability of the previous one. CV = multiplier applied to damage-effect CV.",
  "max_ranks": 4,
  "elements": {
    "Fire": [
      [
        {
          "type": "Heat",
          "cv": 1.0
        }
      ],
      [
        {
          "type": "Impact",
          "cv": 1.0
        }
      ]
    ],
    "Metal": [
      [
        {
          "type": "Physical",
          "cv": 1.0
        }
      ],
      [
        {
          "type": "Lightning",
          "cv": 0.9
        }
      ]
    ],
    "Ice": [
      [],
      []
    ],
    "Nature": [
      [
        {
          "type": "Piercing",
          "cv": 1.0
        },
        {
          "type": "Cut",
          "cv": 1.0
        }
      ],
      [
        {
          "type": "Acid",
          "cv": 1.0
        }
      ]
    ],
    "Blood": [
      [
        {
          "type": "Piercing",
          "cv": 1.0
        },
        {
          "type": "Cut",
          "cv": 1.0
        }
      ],
      [],
      [
        {
          "type": "Mental",
          "cv": 1.0
        }
      ]
    ],
    "Quinta": [
      []
    ]
  },
  "prowess_cards": {}
}